msgspec_ext/__init__.py
msgspec_ext/fast_dotenv.py
msgspec_ext/py.typed
msgspec_ext/settings.py
msgspec_ext/types.py
msgspec_ext/version.py
msgspec_ext-0.5.0.dist-info/METADATA
msgspec_ext-0.5.0.dist-info/WHEEL
msgspec_ext-0.5.0.dist-info/licenses/LICENSE
msgspec_ext-0.5.0.dist-info/RECORD
