Metadata-Version: 2.4
Name: msgspec-ext
Version: 0.5.0
Summary: High-performance settings management and validation library extending msgspec
Project-URL: Homepage, https://github.com/msgflux/msgspec-ext
Project-URL: Documentation, https://github.com/msgflux/msgspec-ext
Project-URL: Repository, https://github.com/msgflux/msgspec-ext
Author-email: Vilson Rodrigues <vilson@msgflux.com>
License-Expression: MIT
License-File: LICENSE
Keywords: configuration,dotenv,environment-variables,fast,msgspec,performance,pydantic,settings,type-validation,validation,validators
Classifier: Development Status :: 4 - Beta
Classifier: Intended Audience :: Developers
Classifier: Intended Audience :: Science/Research
Classifier: Intended Audience :: System Administrators
Classifier: License :: OSI Approved :: MIT License
Classifier: Operating System :: MacOS :: MacOS X
Classifier: Operating System :: Microsoft :: Windows
Classifier: Operating System :: POSIX :: Linux
Classifier: Programming Language :: Python
Classifier: Programming Language :: Python :: 3.10
Classifier: Programming Language :: Python :: 3.11
Classifier: Programming Language :: Python :: 3.12
Classifier: Programming Language :: Python :: 3.13
Classifier: Topic :: Software Development :: Libraries
Classifier: Topic :: Software Development :: Libraries :: Python Modules
Classifier: Topic :: System :: Systems Administration
Classifier: Typing :: Typed
Requires-Python: >=3.10
Requires-Dist: msgspec>=0.19.0
